{
  "slug": "alimenty-na-druzhynu",
  "cat": "family",
  "title": "Аліменти на дружину або чоловіка",
  "h1": "Аліменти на утримання одного з подружжя",
  "desc": "У яких випадках один із подружжя має право на утримання від іншого, зокрема під час вагітності та догляду за дитиною.",
  "order": 12,
  "date_published": "2026-07-01",
  "date_modified": "2026-07-11",
  "blocks": [
    {
      "type": "p",
      "text": "Право на аліменти має не лише дитина. За певних умов один із подружжя (або колишнього подружжя) може вимагати утримання від іншого."
    },
    {
      "type": "h2",
      "text": "Хто має право"
    },
    {
      "type": "ul",
      "items": [
        "той із подружжя, хто є непрацездатним і потребує допомоги;",
        "дружина під час вагітності;",
        "той із батьків, хто доглядає за дитиною до трьох років (а за наявності вади здоров'я дитини — до шести);",
        "той, хто доглядає за дитиною з інвалідністю."
      ]
    },
    {
      "type": "h2",
      "text": "Умови"
    },
    {
      "type": "p",
      "text": "Ключова умова — другий із подружжя має змогу надавати матеріальну допомогу. Суд оцінює сімейний і майновий стан обох сторін."
    },
    {
      "type": "h2",
      "text": "Розмір і форма"
    },
    {
      "type": "p",
      "text": "Аліменти присуджуються у частці від доходу або у твердій грошовій сумі, найчастіше щомісячно. Сторони можуть врегулювати питання договором про утримання, зокрема нотаріальним."
    },
    {
      "type": "h2",
      "text": "Коли право припиняється"
    },
    {
      "type": "p",
      "text": "Право на утримання може припинитися, зокрема, у разі поновлення працездатності, реєстрації нового шлюбу того, хто отримує аліменти, або за рішенням суду."
    }
  ],
  "faq": [
    {
      "q": "Хто має право на аліменти від подружжя?",
      "a": "Непрацездатний із подружжя, вагітна дружина, той, хто доглядає малолітню дитину."
    },
    {
      "q": "Як стягнути такі аліменти?",
      "a": "За договором про утримання або через суд."
    },
    {
      "q": "Коли право на аліменти припиняється?",
      "a": "Зокрема при поновленні працездатності або новому шлюбі одержувача."
    }
  ]
}