{
  "slug": "pozbavlennya-prav",
  "cat": "auto",
  "title": "Позбавлення водійських прав: оскарження",
  "h1": "Позбавлення водійських прав: як захиститися",
  "desc": "За що можуть позбавити водійських прав, як побудувати захист і які порушення в оформленні протоколу дають шанс на скасування.",
  "order": 32,
  "date_published": "2026-07-01",
  "date_modified": "2026-07-11",
  "blocks": [
    {
      "type": "p",
      "text": "Позбавлення права керування — одне з найсуворіших адміністративних стягнень для водія. Але постанова не завжди законна, і в багатьох випадках її вдається скасувати."
    },
    {
      "type": "h2",
      "text": "За що позбавляють"
    },
    {
      "type": "ul",
      "items": [
        "керування у стані сп'яніння;",
        "відмова від огляду на стан сп'яніння;",
        "залишення місця ДТП;",
        "повторні грубі порушення."
      ]
    },
    {
      "type": "h2",
      "text": "На що звернути увагу"
    },
    {
      "type": "p",
      "text": "Часто справа тримається на протоколі та процедурі огляду. Порушення порядку огляду, відсутність понятих чи відео, розбіжності в документах — усе це підстави ставити під сумнів доказ."
    },
    {
      "type": "h2",
      "text": "Строк оскарження"
    },
    {
      "type": "p",
      "text": "Постанову можна оскаржити протягом визначеного законом короткого строку. Зволікання позбавляє права на оскарження, тому діяти треба одразу."
    },
    {
      "type": "h2",
      "text": "Захист"
    },
    {
      "type": "p",
      "text": "Лінія захисту будується на аналізі кожного доказу й дотримання процедури. Навіть за фактичного порушення процесуальні огріхи можуть призвести до закриття справи. <a href=\"../index.html#contacts\">зв'яжіться зі мною</a>."
    }
  ],
  "faq": [
    {
      "q": "За що позбавляють водійських прав?",
      "a": "За керування у стані сп'яніння, відмову від огляду, залишення місця ДТП."
    },
    {
      "q": "Чи можна оскаржити позбавлення прав?",
      "a": "Так, часто через порушення процедури огляду чи оформлення протоколу."
    },
    {
      "q": "Який строк оскарження?",
      "a": "Короткий строк, встановлений законом, тому діяти треба одразу."
    }
  ]
}